{
    "name": "dfhack-32",
    "no-autogen": true,
    "only-arches": [ "i386" ],
    "sources": [
        {
            "type": "archive",
            "url": "https://github.com/DFHack/dfhack/releases/download/0.43.05-beta2/dfhack-0.43.05-beta2-Linux-32-gcc-4.8.1.tar.bz2",
            "sha256": "2e404b67e5c914b7513e942870ff5f3744d147440ae7bc7687c3d97a8c81c7ca",
            "strip-components": 0
        },
        {
            "type": "file",
            "path": "Makefile",
            "dest-filename": "Makefile"
        }
    ]
}
